flvmeta_timestamp_analyzer/__init__.py
flvmeta_timestamp_analyzer/__main__.py
flvmeta_timestamp_analyzer/analyzer.py
flvmeta_timestamp_analyzer/mcp_fastmcp.py
flvmeta_timestamp_analyzer/mcp_server.py
flvmeta_timestamp_analyzer-1.0.10.dist-info/licenses/LICENSE
flvmeta_timestamp_analyzer-1.0.10.dist-info/METADATA
flvmeta_timestamp_analyzer-1.0.10.dist-info/WHEEL
flvmeta_timestamp_analyzer-1.0.10.dist-info/entry_points.txt
flvmeta_timestamp_analyzer-1.0.10.dist-info/top_level.txt
flvmeta_timestamp_analyzer-1.0.10.dist-info/RECORD
