Metadata-Version: 2.4
Name: flvmeta-timestamp-analyzer
Version: 1.0.10
Summary: FLV音视频时间戳分析工具，支持MCP协议和FastMCP框架
Home-page: https://github.com/Soar-Coding-Life/flvmeta-timestamp-analyzer
Author: CoderWGB
Author-email: 864562082@qq.com
License: MIT
Classifier: Development Status :: 4 - Beta
Classifier: Intended Audience :: Developers
Classifier: Topic :: Multimedia :: Video
Classifier: Programming Language :: Python :: 3
Classifier: Programming Language :: Python :: 3.6
Classifier: Programming Language :: Python :: 3.7
Classifier: Programming Language :: Python :: 3.8
Classifier: Programming Language :: Python :: 3.9
Classifier: Programming Language :: Python :: 3.10
Classifier: Programming Language :: Python :: 3.11
Classifier: Programming Language :: Python :: 3.12
Classifier: Programming Language :: Python :: 3.13
Classifier: Operating System :: OS Independent
Classifier: Operating System :: Microsoft :: Windows
Classifier: Operating System :: POSIX :: Linux
Classifier: Operating System :: MacOS
Requires-Python: >=3.6
License-File: LICENSE
Requires-Dist: pyecharts>=2.0.0
Provides-Extra: fastmcp
Requires-Dist: fastmcp; extra == "fastmcp"
Requires-Dist: mcp; extra == "fastmcp"
Requires-Dist: pydantic; extra == "fastmcp"
Dynamic: author
Dynamic: author-email
Dynamic: classifier
Dynamic: description
Dynamic: description-content-type
Dynamic: home-page
Dynamic: license
Dynamic: license-file
Dynamic: provides-extra
Dynamic: requires-dist
Dynamic: requires-python
Dynamic: summary
